plate_layout/__about__.py
plate_layout/__init__.py
plate_layout/cli.py
plate_layout/pl_logger.py
plate_layout/plate_layout.py
plate_layout-1.6.1.dist-info/METADATA
plate_layout-1.6.1.dist-info/WHEEL
plate_layout-1.6.1.dist-info/entry_points.txt
plate_layout-1.6.1.dist-info/licenses/LICENSE.txt
plate_layout-1.6.1.dist-info/RECORD
