Metadata-Version: 2.1
Name: plate-layout
Version: 1.6.1
Summary: A tool to create and visualize sample layouts for multiwell plates.
Project-URL: Source, https://github.com/ssi-dk/CD-MRG-plate_layout
Author-email: "Filip (Persson) Ljung" <filip.persson@gmail.com>
License-Expression: MIT
License-File: LICENSE.txt
Classifier: Development Status :: 4 - Beta
Classifier: Programming Language :: Python
Classifier: Programming Language :: Python :: 3.9
Classifier: Programming Language :: Python :: 3.10
Classifier: Programming Language :: Python :: 3.11
Classifier: Programming Language :: Python :: Implementation :: CPython
Classifier: Programming Language :: Python :: Implementation :: PyPy
Requires-Python: >=3.9
Requires-Dist: matplotlib
Requires-Dist: numpy
Requires-Dist: openpyxl
Requires-Dist: pandas
Requires-Dist: tomli
